cognite/power/__init__.py
cognite/power/_api/__init__.py
cognite/power/_api/generic_power.py
cognite/power/_api/power_transformer_ends_api.py
cognite/power/client.py
cognite/power/data_classes.py
cognite/power/exceptions.py
cognite/power/power_area.py
cognite/power/power_corridor.py
cognite/power/power_graph.py
cognite/power/power_plot.py
cognite/power/py.typed
cognite_power_sdk-0.17.0.dist-info/LICENSE
cognite_power_sdk-0.17.0.dist-info/WHEEL
cognite_power_sdk-0.17.0.dist-info/METADATA
cognite_power_sdk-0.17.0.dist-info/RECORD
