Metadata-Version: 2.1
Name: cognite-power-sdk
Version: 0.17.0
Summary: Cognite Power SDK
Author: Sander Land
Author-email: sander.land@cognite.com
Requires-Python: >=3.6.1,<4.0.0
Classifier: Programming Language :: Python :: 3
Classifier: Programming Language :: Python :: 3.7
Classifier: Programming Language :: Python :: 3.8
Classifier: Programming Language :: Python :: 3.9
Requires-Dist: cognite-sdk (>=2.10.1)
Requires-Dist: matplotlib (>=3.2.1,<4.0.0)
Requires-Dist: networkx (>=2.4,<3.0)
Requires-Dist: numpy (>=1.18.1,<2.0.0)
Requires-Dist: pandas (>=1.0.5,<2.0.0)
Requires-Dist: plotly (>=4.5.4,<5.0.0)
Requires-Dist: pyproj (>=2.6.0,<3.0.0)
Requires-Dist: textdistance (>=4.2.0,<5.0.0)
